aiocapsule/__init__.py
aiocapsule/_modidx.py
aiocapsule/core.py
aiocapsule-0.0.2.dist-info/LICENSE
aiocapsule-0.0.2.dist-info/METADATA
aiocapsule-0.0.2.dist-info/WHEEL
aiocapsule-0.0.2.dist-info/entry_points.txt
aiocapsule-0.0.2.dist-info/top_level.txt
aiocapsule-0.0.2.dist-info/RECORD
