Metadata-Version: 2.1
Name: aiocapsule
Version: 0.0.2
Summary: Simple wrapper for AIOHTTP client session, request and response
Home-page: https://github.com/woncoh1/aiocapsule
Author: woncoh1
Author-email: woncoh1@gmail.com
License: Apache Software License 2.0
Keywords: nbdev jupyter notebook python
Platform: UNKNOWN
Classifier: Development Status :: 4 - Beta
Classifier: Intended Audience :: Developers
Classifier: Natural Language :: English
Classifier: Programming Language :: Python :: 3.7
Classifier: Programming Language :: Python :: 3.8
Classifier: Programming Language :: Python :: 3.9
Classifier: Programming Language :: Python :: 3.10
Classifier: License :: OSI Approved :: Apache Software License
Requires-Python: >=3.7
License-File: LICENSE
Requires-Dist: aiohttp (==3.8.4)
Provides-Extra: dev
